faceit_friends/__init__.py
faceit_friends-1.0.1.dist-info/LICENSE.txt
faceit_friends-1.0.1.dist-info/METADATA
faceit_friends-1.0.1.dist-info/WHEEL
faceit_friends-1.0.1.dist-info/top_level.txt
faceit_friends-1.0.1.dist-info/RECORD
