Metadata-Version: 2.1
Name: faceit-friends
Version: 1.0.1
Summary: Scraps friend's friends from Faceit.
Home-page: https://github.com/PavelBorsh/faceit_friends
Author: Pavel Borshchevsky
Author-email: 3410914@gmail.com
License: UNKNOWN
Platform: UNKNOWN
Classifier: Programming Language :: Python :: 3
Classifier: License :: OSI Approved :: MIT License
Classifier: Operating System :: OS Independent
Requires-Python: >=3.6
Requires-Dist: psutil (>=5)
Requires-Dist: selenium (>=3)
Requires-Dist: urllib3 (>=1.25)
